Workbook

Sheet Summary
A1: Strategy Auditor: business plan summary
A2: Two scenarios over 12 months, priced per audit. Change inputs on the Assumptions sheet; everything here recalculates. LLM cost per audit is an ESTIMATE (Assumptions!B5) until M2 measures it.
A4: Metric | B4: Base | C4: Growth | D4: Unit
A5: LLM cost per audit (ESTIMATE, Assumptions!B5) | B5: =Assumptions!$B$5 | C5: =Assumptions!$B$5 | D5: $ / audit
A6: Contribution per audit, pay per audit | B6: =Unit_Economics!B9 | C6: =Unit_Economics!C9 | D6: $ / audit
A7: Gross margin per audit | B7: =Unit_Economics!B10 | C7: =Unit_Economics!C10 | D7: %
A8: Contribution per hobbyist subscriber | B8: =Unit_Economics!B17 | C8: =Unit_Economics!C17 | D8: $ / month
A9: Gross margin per subscriber | B9: =Unit_Economics!B18 | C9: =Unit_Economics!C18 | D9: %
A10: LTV to CAC (blended) | B10: =Unit_Economics!B27 | C10: =Unit_Economics!C27 | D10: x
A11: Paying users, month 6 | B11: =Model_Base!H9 | C11: =Model_Growth!H9 | D11: users
A12: Paying users, month 12 | B12: =Model_Base!N9 | C12: =Model_Growth!N9 | D12: users
A13: Audits run, month 12 | B13: =Model_Base!N15 | C13: =Model_Growth!N15 | D13: audits
A14: Revenue, month 12 | B14: =Model_Base!N19 | C14: =Model_Growth!N19 | D14: $ / month
A15: Gross margin, month 12 | B15: =Model_Base!N24 | C15: =Model_Growth!N24 | D15: %
A16: Revenue, months 1-12 | B16: =SUM(Model_Base!C19:N19) | C16: =SUM(Model_Growth!C19:N19) | D16: $
A17: LLM cost, months 1-12 | B17: =SUM(Model_Base!C21:N21) | C17: =SUM(Model_Growth!C21:N21) | D17: $
A18: Operating profit, months 1-12 | B18: =SUM(Model_Base!C30:N30) | C18: =SUM(Model_Growth!C30:N30) | D18: $
A19: Lowest cash balance | B19: =MIN(Model_Base!C33:N33) | C19: =MIN(Model_Growth!C33:N33) | D19: $
A20: Cash, end of month 12 | B20: =Model_Base!N33 | C20: =Model_Growth!N33 | D20: $
A21: Runway: first month cash goes below zero | B21: =IF(SUM(Model_Base!C35:N35)=0,"none within 12 months",MATCH(1,Model_Base!C35:N35,0)) | C21: =IF(SUM(Model_Growth!C35:N35)=0,"none within 12 months",MATCH(1,Model_Growth!C35:N35,0)) | D21: month
A22: Runway left after month 12 at that month's burn | B22: =IF(Model_Base!N30>=0,"not burning cash",MAX(0,Model_Base!N33/-Model_Base!N30)) | C22: =IF(Model_Growth!N30>=0,"not burning cash",MAX(0,Model_Growth!N33/-Model_Growth!N30)) | D22: months
A23: Break-even: first month of operating profit | B23: =IF(SUM(Model_Base!C36:N36)=0,"not within 12 months",MATCH(1,Model_Base!C36:N36,0)) | C23: =IF(SUM(Model_Growth!C36:N36)=0,"not within 12 months",MATCH(1,Model_Growth!C36:N36,0)) | D23: month
A24: Funding needed to never go below zero | B24: =MAX(0,-MIN(Model_Base!C33:N33)) | C24: =MAX(0,-MIN(Model_Growth!C33:N33)) | D24: $
A27: How to read this:
A28: - One audit = one trading idea in, one evidence-backed verdict out. Sold per audit ($2, in packs of 5) or as a hobbyist plan ($15/month, 20 audits): both are pricing hypotheses.
A29: - LLM cost per audit is a bottom-up ESTIMATE from the code (Cost_Estimate sheet), at DeepSeek peak prices. It is replaced with the measured figure after M2.
A30: - Variable cost is a few cents an audit, so margins are set by price and card fees; the plan is decided by users, churn, CAC and team cost (owner estimates, yellow on Assumptions).
A31: - No fees or taxes beyond card processing are modeled. The auditor gives research verdicts, not financial advice.

Sheet Assumptions
A1: Strategy Auditor: business model assumptions
A2: Legend: blue = input you can change. Yellow = estimate or hypothesis to confirm (not measured). Black = formula. Green = link to another sheet. Column B feeds Model_Base, column C feeds Model_Growth.
A3: Product: the Strategy Auditor, a paper-trading research tool. One audit = one trading idea in plain English, one evidence-backed verdict out (kill / inconclusive / promising / cannot audit), tested on 50 US large caps with historical data. Not financial advice. Sold two ways (pricing hypotheses): pay per audit, or a hobbyist plan with a monthly allowance of audits.
A5: LLM cost per audit (USD): ESTIMATE | B5: 0.048 | C5: ESTIMATE | D5: $ / audit | E5: THE single cost variable; both scenarios and every sheet use it. Estimate, not measured: built bottom-up on the Cost_Estimate sheet (0.0476, rounded) from calls per audit, prompt sizes in src/auditor/agents.py and DeepSeek prices in src/llm.py (peak, cache-miss: an upper bound). After M2, type the measured mean cost per audit here: section '9. Cost and trace' of each demo report (cost.usd in state.json), or the neatlogs traces.
A7: Assumption | B7: Base | C7: Growth | D7: Unit | E7: Source or note
A8: Pay-per-audit price (HYPOTHESIS) | B8: 2 | C8: 2 | D8: $ / audit | E8: Pricing hypothesis, not tested with customers.
A9: Audits bought per card charge (credit pack) | B9: 5 | C9: 5 | D9: audits / charge | E9: Hypothesis: audits sold in packs of 5 ($10). Charging every $2 audit separately would let Stripe's $0.30 fixed fee take 15% of revenue; a pack of 5 cuts it to 3%.
A10: Hobbyist plan price (HYPOTHESIS) | B10: 15 | C10: 15 | D10: $ / month | E10: Pricing hypothesis, not tested with customers.
A11: Audits included in the hobbyist plan | B11: 20 | C11: 20 | D11: audits / month | E11: Hypothesis. No overage is sold in this model.
A12: Audits a subscriber runs per month | B12: 10 | C12: 10 | D12: audits / month | E12: Owner estimate. The plan beats pay-per-audit above 7.5 audits a month, so subscribers are the heavier users.
A13: Audits a pay-per-audit user runs per month | B13: 3 | C13: 3 | D13: audits / month | E13: Owner estimate.
A14: Share of users on the hobbyist plan | B14: 0.4 | C14: 0.4 | D14: % | E14: Owner estimate. The rest pay per audit.
A15: Data cost per audit | B15: 0 | C15: 0 | D15: $ / audit | E15: Public data: Yahoo Finance prices and earnings dates, DoltHub options data (implied vol). Free; cached after the first fetch.
A16: Payment fee, share of the charge | B16: 0.029 | C16: 0.029 | D16: % | E16: Stripe standard US card pricing: 2.9% + $0.30 per successful charge.
A17: Payment fee, fixed per charge | B17: 0.3 | C17: 0.3 | D17: $ / charge | E17: Stripe standard US card pricing.
A18: Paying users at start | B18: 0 | C18: 0 | D18: users | E18: Pre-launch.
A19: New paying users in month 1 | B19: 10 | C19: 25 | D19: users | E19: Owner estimate. Base: organic from build-in-public posts. Growth: plus paid acquisition.
... A26: Starting cash | B26: 25000 | C26: 25000 | D26: $ | E26: Owner estimate: founder-funded.

Sheet Cost_Estimate
A1: LLM cost per audit: bottom-up ESTIMATE (not measured)
A2: How Assumptions!B5 was estimated before any real audit ran (AUDITOR_SPEC sections 8 and 13). Replace Assumptions!B5 with the measured figure after M2; this sheet then documents the estimate.
A4: Input | B4: Value | C4: Unit | D4: Source or note
A5: deepseek-v4-pro input price (Planner, Naysayer; thinking on) | B5: 1.32 | C5: $ / 1M tokens | D5: src/llm.py PRICES, read at build time. DeepSeek peak, cache-miss rates: an upper bound; off-peak is half.
A6: deepseek-v4-pro output price (thinking tokens billed as output) | B6: 3.96 | C6: $ / 1M tokens | D6: src/llm.py PRICES.
A7: deepseek-flash input price (Reporter; thinking off) | B7: 0.3 | C7: $ / 1M tokens | D7: src/llm.py PRICES.
A8: deepseek-flash output price | B8: 1.2 | C8: $ / 1M tokens | D8: src/llm.py PRICES.
A9: Characters per token | B9: 4 | C9: chars | D9: Rule of thumb for English and JSON.
A10: Completion tokens per thinking call (thinking + JSON reply) | B10: 3000 | C10: tokens | D10: ASSUMPTION: reasoning_effort high, so most of it is thinking; plausible range 1,500-4,000. The swarm's measured cost implies about 3,900 (sanity check below), so the estimate leans low if anything.
A11: Completion tokens per Reporter call | B11: 300 | C11: tokens | D11: ASSUMPTION: 2 to 5 sentences of prose in JSON.
A12: Chance the first plan is invalid (one Planner fix call) | B12: 0.1 | C12: % | D12: ASSUMPTION. The validator rejects off-menu features, ranges or groups; DeepSeek JSON mode does not enforce the schema.
A13: Retry and contingency uplift | B13: 0.1 | C13: % | D13: Empty or off-schema replies are retried once inside llm(); the retry's tokens are billed (spec section 8).
A16: Call | B16: Agent | C16: Model | D16: Expected calls per audit | E16: System prompt + schema (chars) | F16: User prompt (chars) | G16: Prompt tokens | H16: Completion tokens | I16: Cost per call ($) | J16: Expected cost per audit ($) | K16: Where the prompt size comes from
A17: Planner: idea to plan v0 | B17: planner | C17: deepseek-v4-pro | D17: 1 | E17: 4818 | F17: 60 | G17: =(E17+F17)/$B$9 | H17: =$B$10 | I17: =G17*$B$5/1000000+H17*$B$6/1000000 | J17: =D17*I17 | K17: System: PLANNER_SYSTEM + plan schema, read at build time. User: the idea as JSON, 34-56 chars measured.
A18: Planner: one fix after an invalid plan | B18: planner | C18: deepseek-v4-pro | D18: =$B$12 | E18: 4818 | F18: 300 | G18: =(E18+F18)/$B$9 | H18: =$B$10 | I18: =G18*$B$5/1000000+H18*$B$6/1000000 | J18: =D18*I18 | K18: Only when plan v0 fails validation (spec section 4). User: idea + validator message + instruction.
A19: Naysayer call 1: doubts, choose follow-ups | B19: naysayer | C19: deepseek-v4-pro | D19: 1 | E19: 1824 | F19: 3300 | G19: =(E19+F19)/$B$9 | H19: =$B$10 | I19: =G19*$B$5/1000000+H19*$B$6/1000000 | J19: =D19*I19 | K19: System: NAYSAYER_FOLLOWUPS_SYSTEM (with the F1-F4 menu) + schema, read at build time. User: summary statistics, 2,502-3,262 chars measured.
A20: Naysayer call 2: final critique | B20: naysayer | C20: deepseek-v4-pro | D20: 1 | E20: 926 | F20: 4500 | G20: =(E20+F20)/$B$9 | H20: =$B$10 | I20: =G20*$B$5/1000000+H20*$B$6/1000000 | J20: =D20*I20 | K20: System: NAYSAYER_SYSTEM + schema. User: summary statistics + follow-up results, 3,249-4,019 chars measured.
A21: Reporter: prose on the code-written report | B21: reporter | C21: deepseek-flash | D21: 1 | E21: 699 | F21: 10000 | G21: =(E21+F21)/$B$9 | H21: =$B$11 | I21: =G21*$B$7/1000000+H21*$B$8/1000000 | J21: =D21*I21 | K21: The reserved 8th call, thinking off. User: the report draft, 6,164-7,831 chars measured on 3 synthetic years; real data has 13 year columns in the coverage table.
A22: Total | D22: =SUM(D17:D21) | J22: =SUM(J17:J21)
A24: Expected LLM calls per audit | B24: =D22 | C24: calls | D24: Spec section 4: Planner 1 (+1 only after an invalid plan), Naysayer 2, Reporter 1. Hard budget: 8 calls.
A25: Cost per audit before uplift | B25: =J22 | C25: $ / audit
A26: Estimated LLM cost per audit (ESTIMATE) | B26: =B25*(1+B13) | C26: $ / audit | D26: The bottom-up estimate. Rounded, it is the typed value of Assumptions!B5.
A27: Assumptions!B5, the value the model uses | B27: =Assumptions!B5 | C27: $ / audit | D27: Green link. Holds this estimate until M2, then the measured figure.
A28: Difference: model input minus this estimate | B28: =B27-B26 | C28: $ / audit | D28: Under $0.0005 while B5 is still the estimate (rounding).
A29: Worst case: all 8 budgeted calls (7 thinking + Reporter) | B29: =(7*I17+I21)*(1+B13) | C29: $ / audit | D29: Upper bound if every audit used the full budget.
A30: Same estimate at DeepSeek off-peak rates (half price) | B30: =B26/2 | C30: $ / audit
A32: Sanity check: the trading swarm's measured cost
A33: Swarm LLM cost per decision, measured (upper bound) | B33: 0.038 | C33: $ / decision | D33: results/README.md: $11.76 logged over 310 validation setups on 2026-10-10, DeepSeek peak cache-miss prices.
A34: deepseek-v4-pro thinking calls per swarm decision | B34: 2 | C34: calls | D34: Two Planner rounds per setup (rounds = 2 on all 577 lines of results/swarm_validation.jsonl; Planner made 1,154 of ~1,760 calls, docs/SWARM_SPEC.md section 15). Same model and thinking settings as the auditor.
A35: Implied cost per thinking call | B35: =B33/B34 | C35: $ / call | D35: Upper bound: treats the swarm's deepseek-flash Researcher call and rare Naysayer calls as free.
A36: Bottom-up cost per thinking call (Planner row above) | B36: =I17 | C36: $ / call
A37: Thinking calls per audit | B37: =SUMIF(C17:C21,"deepseek-v4-pro",D17:D21) | C37: calls
A38: Swarm-calibrated cost per audit | B38: =B37*B35+J21 | C38: $ / audit | D38: Thinking calls per audit x the swarm's implied cost per thinking call, + the Reporter call.
A39: Bottom-up estimate as a share of the swarm-calibrated figure | B39: =B26/B38 | C39: x | D39: Below 1: the bottom-up estimate is lower than what the swarm's measured spend suggests. Same order of magnitude either way: a few cents per audit.
A41: Notes
A42: Calls follow the spec at M2 (section 4). M1 'before' runs make one Naysayer call (no follow-ups), so they should come in about one thinking call under this estimate. Update B5 from the M2 runs, as spec section 13 says.
A43: System prompt sizes are read from src/auditor/agents.py when this workbook is built: the system text plus the JSON-schema suffix src/llm.py appends for DeepSeek.
A44: User prompt sizes were measured on 2026-10-11 by running the audit loop with the fake LLM on the synthetic market of tests/test_auditor_run.py, extended to all 50 tickers, for the three demo ideas, then rounded up.
A45: Data costs $0 (Yahoo Finance, DoltHub, both public). Hosting is a fixed monthly cost on Assumptions, not per audit.
A46: To replace the estimate: type the mean measured cost per audit of the demo audits into Assumptions!B5. Source: section '9. Cost and trace' of each report.md (or cost.usd in state.json), cross-checked in neatlogs.

Sheet Model_Base
A1: Base scenario: monthly model (months 1-12)
A2: All values in $ unless the unit column says otherwise. Inputs live on the Assumptions sheet, column B; LLM cost per audit is the single cell Assumptions!B5 (ESTIMATE).
A3: Line | B3: Unit
A4: Month | C4: 1 | D4: =C4+1 | E4: =D4+1 | F4: =E4+1 | G4: =F4+1 | H4: =G4+1 | I4: =H4+1 | J4: =I4+1 | K4: =J4+1 | ... N4: =M4+1
A6: Paying users, start of month | B6: users | C6: =Assumptions!$B$18 | D6: =C9 | E6: =D9 | F6: =E9 | G6: =F9 | H6: =G9 | I6: =H9 | J6: =I9 | K6: =J9 | ... N6: =M9
A7: New users | B7: users | C7: =Assumptions!$B$19*(1+Assumptions!$B$20)^(C4-1) | D7: =Assumptions!$B$19*(1+Assumptions!$B$20)^(D4-1) | E7: =Assumptions!$B$19*(1+Assumptions!$B$20)^(E4-1) | F7: =Assumptions!$B$19*(1+Assumptions!$B$20)^(F4-1) | G7: =Assumptions!$B$19*(1+Assumptions!$B$20)^(G4-1) | H7: =Assumptions!$B$19*(1+Assumptions!$B$20)^(H4-1) | I7: =Assumptions!$B$19*(1+Assumptions!$B$20)^(I4-1) | J7: =Assumptions!$B$19*(1+Assumptions!$B$20)^(J4-1) | ... N7: =Assumptions!$B$19*(1+Assumptions!$B$20)^(N4-1)
A8: Churned users | B8: users | C8: =C6*Assumptions!$B$21 | D8: =D6*Assumptions!$B$21 | E8: =E6*Assumptions!$B$21 | F8: =F6*Assumptions!$B$21 | G8: =G6*Assumptions!$B$21 | H8: =H6*Assumptions!$B$21 | I8: =I6*Assumptions!$B$21 | J8: =J6*Assumptions!$B$21 | ... N8: =N6*Assumptions!$B$21
A9: Paying users, end of month | B9: users | C9: =C6+C7-C8 | D9: =D6+D7-D8 | E9: =E6+E7-E8 | F9: =F6+F7-F8 | G9: =G6+G7-G8 | H9: =H6+H7-H8 | I9: =I6+I7-I8 | J9: =J6+J7-J8 | ... N9: =N6+N7-N8
A10: on the hobbyist plan | B10: users | C10: =C9*Assumptions!$B$14 | D10: =D9*Assumptions!$B$14 | E10: =E9*Assumptions!$B$14 | F10: =F9*Assumptions!$B$14 | G10: =G9*Assumptions!$B$14 | H10: =H9*Assumptions!$B$14 | I10: =I9*Assumptions!$B$14 | J10: =J9*Assumptions!$B$14 | ... N10: =N9*Assumptions!$B$14
A11: paying per audit | B11: users | C11: =C9-C10 | D11: =D9-D10 | E11: =E9-E10 | F11: =F9-F10 | G11: =G9-G10 | H11: =H9-H10 | I11: =I9-I10 | J11: =J9-J10 | ... N11: =N9-N10
A13: Audits run by subscribers | B13: audits | C13: =C10*Assumptions!$B$12 | D13: =D10*Assumptions!$B$12 | E13: =E10*Assumptions!$B$12 | F13: =F10*Assumptions!$B$12 | G13: =G10*Assumptions!$B$12 | H13: =H10*Assumptions!$B$12 | I13: =I10*Assumptions!$B$12 | J13: =J10*Assumptions!$B$12 | ... N13: =N10*Assumptions!$B$12
A14: Audits bought per audit | B14: audits | C14: =C11*Assumptions!$B$13 | D14: =D11*Assumptions!$B$13 | E14: =E11*Assumptions!$B$13 | F14: =F11*Assumptions!$B$13 | G14: =G11*Assumptions!$B$13 | H14: =H11*Assumptions!$B$13 | I14: =I11*Assumptions!$B$13 | J14: =J11*Assumptions!$B$13 | ... N14: =N11*Assumptions!$B$13
A15: Audits run | B15: audits | C15: =C13+C14 | D15: =D13+D14 | E15: =E13+E14 | F15: =F13+F14 | G15: =G13+G14 | H15: =H13+H14 | I15: =I13+I14 | J15: =J13+J14 | ... N15: =N13+N14
A17: Revenue: hobbyist plan | B17: $ | C17: =C10*Assumptions!$B$10 | D17: =D10*Assumptions!$B$10 | E17: =E10*Assumptions!$B$10 | F17: =F10*Assumptions!$B$10 | G17: =G10*Assumptions!$B$10 | H17: =H10*Assumptions!$B$10 | I17: =I10*Assumptions!$B$10 | J17: =J10*Assumptions!$B$10 | ... N17: =N10*Assumptions!$B$10
A18: Revenue: pay per audit | B18: $ | C18: =C14*Assumptions!$B$8 | D18: =D14*Assumptions!$B$8 | E18: =E14*Assumptions!$B$8 | F18: =F14*Assumptions!$B$8 | G18: =G14*Assumptions!$B$8 | H18: =H14*Assumptions!$B$8 | I18: =I14*Assumptions!$B$8 | J18: =J14*Assumptions!$B$8 | ... N18: =N14*Assumptions!$B$8
A19: Revenue | B19: $ | C19: =C17+C18 | D19: =D17+D18 | E19: =E17+E18 | F19: =F17+F18 | G19: =G17+G18 | H19: =H17+H18 | I19: =I17+I18 | J19: =J17+J18 | ... N19: =N17+N18
A20: Payment fees | B20: $ | C20: =C10*(Assumptions!$B$10*Assumptions!$B$16+Assumptions!$B$17)+C14*(Assumptions!$B$8*Assumptions!$B$16+Assumptions!$B$17/Assumptions!$B$9) | D20: =D10*(Assumptions!$B$10*Assumptions!$B$16+Assumptions!$B$17)+D14*(Assumptions!$B$8*Assumptions!$B$16+Assumptions!$B$17/Assumptions!$B$9) | E20: =E10*(Assumptions!$B$10*Assumptions!$B$16+Assumptions!$B$17)+E14*(Assumptions!$B$8*Assumptions!$B$16+Assumptions!$B$17/Assumptions!$B$9) | F20: =F10*(Assumptions!$B$10*Assumptions!$B$16+Assumptions!$B$17)+F14*(Assumptions!$B$8*Assumptions!$B$16+Assumptions!$B$17/Assumptions!$B$9) | G20: =G10*(Assumptions!$B$10*Assumptions!$B$16+Assumptions!$B$17)+G14*(Assumptions!$B$8*Assumptions!$B$16+Assumptions!$B$17/Assumptions!$B$9) | H20: =H10*(Assumptions!$B$10*Assumptions!$B$16+Assumptions!$B$17)+H14*(Assumptions!$B$8*Assumptions!$B$16+Assumptions!$B$17/Assumptions!$B$9) | I20: =I10*(Assumptions!$B$10*Assumptions!$B$16+Assumptions!$B$17)+I14*(Assumptions!$B$8*Assumptions!$B$16+Assumptions!$B$17/Assumptions!$B$9) | J20: =J10*(Assumptions!$B$10*Assumptions!$B$16+Assumptions!$B$17)+J14*(Assumptions!$B$8*Assumptions!$B$16+Assumptions!$B$17/Assumptions!$B$9) | ... N20: =N10*(Assumptions!$B$10*Assumptions!$B$16+Assumptions!$B$17)+N14*(Assumptions!$B$8*Assumptions!$B$16+Assumptions!$B$17/Assumptions!$B$9)
A21: LLM inference (audits x cost per audit) | B21: $ | C21: =C15*Assumptions!$B$5 | D21: =D15*Assumptions!$B$5 | E21: =E15*Assumptions!$B$5 | F21: =F15*Assumptions!$B$5 | G21: =G15*Assumptions!$B$5 | H21: =H15*Assumptions!$B$5 | I21: =I15*Assumptions!$B$5 | J21: =J15*Assumptions!$B$5 | ... N21: =N15*Assumptions!$B$5
A22: Data (audits x data cost per audit) | B22: $ | C22: =C15*Assumptions!$B$15 | D22: =D15*Assumptions!$B$15 | E22: =E15*Assumptions!$B$15 | F22: =F15*Assumptions!$B$15 | G22: =G15*Assumptions!$B$15 | H22: =H15*Assumptions!$B$15 | I22: =I15*Assumptions!$B$15 | J22: =J15*Assumptions!$B$15 | ... N22: =N15*Assumptions!$B$15
A23: Gross profit | B23: $ | C23: =C19-C20-C21-C22 | D23: =D19-D20-D21-D22 | E23: =E19-E20-E21-E22 | F23: =F19-F20-F21-F22 | G23: =G19-G20-G21-G22 | H23: =H19-H20-H21-H22 | I23: =I19-I20-I21-I22 | J23: =J19-J20-J21-J22 | ... N23: =N19-N20-N21-N22
A24: Gross margin | B24: % | C24: =IF(C19=0,0,C23/C19) | D24: =IF(D19=0,0,D23/D19) | E24: =IF(E19=0,0,E23/E19) | F24: =IF(F19=0,0,F23/F19) | G24: =IF(G19=0,0,G23/G19) | H24: =IF(H19=0,0,H23/H19) | I24: =IF(I19=0,0,I23/I19) | J24: =IF(J19=0,0,J23/J19) | ... N24: =IF(N19=0,0,N23/N19)
A26: Marketing (new users x CAC) | B26: $ | C26: =C7*Assumptions!$B$22 | D26: =D7*Assumptions!$B$22 | E26: =E7*Assumptions!$B$22 | F26: =F7*Assumptions!$B$22 | G26: =G7*Assumptions!$B$22 | H26: =H7*Assumptions!$B$22 | I26: =I7*Assumptions!$B$22 | J26: =J7*Assumptions!$B$22 | ... N26: =N7*Assumptions!$B$22
A27: Hosting | B27: $ | C27: =Assumptions!$B$23 | D27: =Assumptions!$B$23 | E27: =Assumptions!$B$23 | F27: =Assumptions!$B$23 | G27: =Assumptions!$B$23 | H27: =Assumptions!$B$23 | I27: =Assumptions!$B$23 | J27: =Assumptions!$B$23 | ... N27: =Assumptions!$B$23
A28: neatlogs | B28: $ | C28: =Assumptions!$B$24 | D28: =Assumptions!$B$24 | E28: =Assumptions!$B$24 | F28: =Assumptions!$B$24 | G28: =Assumptions!$B$24 | H28: =Assumptions!$B$24 | I28: =Assumptions!$B$24 | J28: =Assumptions!$B$24 | ... N28: =Assumptions!$B$24
A29: Team | B29: $ | C29: =Assumptions!$B$25 | D29: =Assumptions!$B$25 | E29: =Assumptions!$B$25 | F29: =Assumptions!$B$25 | G29: =Assumptions!$B$25 | H29: =Assumptions!$B$25 | I29: =Assumptions!$B$25 | J29: =Assumptions!$B$25 | ... N29: =Assumptions!$B$25
A30: Operating profit | B30: $ | C30: =C23-C26-C27-C28-C29 | D30: =D23-D26-D27-D28-D29 | E30: =E23-E26-E27-E28-E29 | F30: =F23-F26-F27-F28-F29 | G30: =G23-G26-G27-G28-G29 | H30: =H23-H26-H27-H28-H29 | I30: =I23-I26-I27-I28-I29 | J30: =J23-J26-J27-J28-J29 | ... N30: =N23-N26-N27-N28-N29
A32: Cash, start of month | B32: $ | C32: =Assumptions!$B$26 | D32: =C33 | E32: =D33 | F32: =E33 | G32: =F33 | H32: =G33 | I32: =H33 | J32: =I33 | K32: =J33 | ... N32: =M33
A33: Cash, end of month | B33: $ | C33: =C32+C30 | D33: =D32+D30 | E33: =E32+E30 | F33: =F32+F30 | G33: =G32+G30 | H33: =H32+H30 | I33: =I32+I30 | J33: =J32+J30 | ... N33: =N32+N30
A35: Flag: cash below zero (1 = yes) | B35: flag | C35: =IF(C33<0,1,0) | D35: =IF(D33<0,1,0) | E35: =IF(E33<0,1,0) | F35: =IF(F33<0,1,0) | G35: =IF(G33<0,1,0) | H35: =IF(H33<0,1,0) | I35: =IF(I33<0,1,0) | J35: =IF(J33<0,1,0) | ... N35: =IF(N33<0,1,0)
A36: Flag: operating profit at or above zero (1 = yes) | B36: flag | C36: =IF(C30>=0,1,0) | D36: =IF(D30>=0,1,0) | E36: =IF(E30>=0,1,0) | F36: =IF(F30>=0,1,0) | G36: =IF(G30>=0,1,0) | H36: =IF(H30>=0,1,0) | I36: =IF(I30>=0,1,0) | J36: =IF(J30>=0,1,0) | ... N36: =IF(N30>=0,1,0)

Sheet Model_Growth
A1: Growth scenario: monthly model (months 1-12)
A2: All values in $ unless the unit column says otherwise. Inputs live on the Assumptions sheet, column C; LLM cost per audit is the single cell Assumptions!B5 (ESTIMATE).
A3: Line | B3: Unit
A4: Month | C4: 1 | D4: =C4+1 | E4: =D4+1 | F4: =E4+1 | G4: =F4+1 | H4: =G4+1 | I4: =H4+1 | J4: =I4+1 | K4: =J4+1 | ... N4: =M4+1
A6: Paying users, start of month | B6: users | C6: =Assumptions!$C$18 | D6: =C9 | E6: =D9 | F6: =E9 | G6: =F9 | H6: =G9 | I6: =H9 | J6: =I9 | K6: =J9 | ... N6: =M9
A7: New users | B7: users | C7: =Assumptions!$C$19*(1+Assumptions!$C$20)^(C4-1) | D7: =Assumptions!$C$19*(1+Assumptions!$C$20)^(D4-1) | E7: =Assumptions!$C$19*(1+Assumptions!$C$20)^(E4-1) | F7: =Assumptions!$C$19*(1+Assumptions!$C$20)^(F4-1) | G7: =Assumptions!$C$19*(1+Assumptions!$C$20)^(G4-1) | H7: =Assumptions!$C$19*(1+Assumptions!$C$20)^(H4-1) | I7: =Assumptions!$C$19*(1+Assumptions!$C$20)^(I4-1) | J7: =Assumptions!$C$19*(1+Assumptions!$C$20)^(J4-1) | ... N7: =Assumptions!$C$19*(1+Assumptions!$C$20)^(N4-1)
A8: Churned users | B8: users | C8: =C6*Assumptions!$C$21 | D8: =D6*Assumptions!$C$21 | E8: =E6*Assumptions!$C$21 | F8: =F6*Assumptions!$C$21 | G8: =G6*Assumptions!$C$21 | H8: =H6*Assumptions!$C$21 | I8: =I6*Assumptions!$C$21 | J8: =J6*Assumptions!$C$21 | ... N8: =N6*Assumptions!$C$21
A9: Paying users, end of month | B9: users | C9: =C6+C7-C8 | D9: =D6+D7-D8 | E9: =E6+E7-E8 | F9: =F6+F7-F8 | G9: =G6+G7-G8 | H9: =H6+H7-H8 | I9: =I6+I7-I8 | J9: =J6+J7-J8 | ... N9: =N6+N7-N8
A10: on the hobbyist plan | B10: users | C10: =C9*Assumptions!$C$14 | D10: =D9*Assumptions!$C$14 | E10: =E9*Assumptions!$C$14 | F10: =F9*Assumptions!$C$14 | G10: =G9*Assumptions!$C$14 | H10: =H9*Assumptions!$C$14 | I10: =I9*Assumptions!$C$14 | J10: =J9*Assumptions!$C$14 | ... N10: =N9*Assumptions!$C$14
A11: paying per audit | B11: users | C11: =C9-C10 | D11: =D9-D10 | E11: =E9-E10 | F11: =F9-F10 | G11: =G9-G10 | H11: =H9-H10 | I11: =I9-I10 | J11: =J9-J10 | ... N11: =N9-N10
A13: Audits run by subscribers | B13: audits | C13: =C10*Assumptions!$C$12 | D13: =D10*Assumptions!$C$12 | E13: =E10*Assumptions!$C$12 | F13: =F10*Assumptions!$C$12 | G13: =G10*Assumptions!$C$12 | H13: =H10*Assumptions!$C$12 | I13: =I10*Assumptions!$C$12 | J13: =J10*Assumptions!$C$12 | ... N13: =N10*Assumptions!$C$12
A14: Audits bought per audit | B14: audits | C14: =C11*Assumptions!$C$13 | D14: =D11*Assumptions!$C$13 | E14: =E11*Assumptions!$C$13 | F14: =F11*Assumptions!$C$13 | G14: =G11*Assumptions!$C$13 | H14: =H11*Assumptions!$C$13 | I14: =I11*Assumptions!$C$13 | J14: =J11*Assumptions!$C$13 | ... N14: =N11*Assumptions!$C$13
A15: Audits run | B15: audits | C15: =C13+C14 | D15: =D13+D14 | E15: =E13+E14 | F15: =F13+F14 | G15: =G13+G14 | H15: =H13+H14 | I15: =I13+I14 | J15: =J13+J14 | ... N15: =N13+N14
A17: Revenue: hobbyist plan | B17: $ | C17: =C10*Assumptions!$C$10 | D17: =D10*Assumptions!$C$10 | E17: =E10*Assumptions!$C$10 | F17: =F10*Assumptions!$C$10 | G17: =G10*Assumptions!$C$10 | H17: =H10*Assumptions!$C$10 | I17: =I10*Assumptions!$C$10 | J17: =J10*Assumptions!$C$10 | ... N17: =N10*Assumptions!$C$10
A18: Revenue: pay per audit | B18: $ | C18: =C14*Assumptions!$C$8 | D18: =D14*Assumptions!$C$8 | E18: =E14*Assumptions!$C$8 | F18: =F14*Assumptions!$C$8 | G18: =G14*Assumptions!$C$8 | H18: =H14*Assumptions!$C$8 | I18: =I14*Assumptions!$C$8 | J18: =J14*Assumptions!$C$8 | ... N18: =N14*Assumptions!$C$8
A19: Revenue | B19: $ | C19: =C17+C18 | D19: =D17+D18 | E19: =E17+E18 | F19: =F17+F18 | G19: =G17+G18 | H19: =H17+H18 | I19: =I17+I18 | J19: =J17+J18 | ... N19: =N17+N18
A20: Payment fees | B20: $ | C20: =C10*(Assumptions!$C$10*Assumptions!$C$16+Assumptions!$C$17)+C14*(Assumptions!$C$8*Assumptions!$C$16+Assumptions!$C$17/Assumptions!$C$9) | D20: =D10*(Assumptions!$C$10*Assumptions!$C$16+Assumptions!$C$17)+D14*(Assumptions!$C$8*Assumptions!$C$16+Assumptions!$C$17/Assumptions!$C$9) | E20: =E10*(Assumptions!$C$10*Assumptions!$C$16+Assumptions!$C$17)+E14*(Assumptions!$C$8*Assumptions!$C$16+Assumptions!$C$17/Assumptions!$C$9) | F20: =F10*(Assumptions!$C$10*Assumptions!$C$16+Assumptions!$C$17)+F14*(Assumptions!$C$8*Assumptions!$C$16+Assumptions!$C$17/Assumptions!$C$9) | G20: =G10*(Assumptions!$C$10*Assumptions!$C$16+Assumptions!$C$17)+G14*(Assumptions!$C$8*Assumptions!$C$16+Assumptions!$C$17/Assumptions!$C$9) | H20: =H10*(Assumptions!$C$10*Assumptions!$C$16+Assumptions!$C$17)+H14*(Assumptions!$C$8*Assumptions!$C$16+Assumptions!$C$17/Assumptions!$C$9) | I20: =I10*(Assumptions!$C$10*Assumptions!$C$16+Assumptions!$C$17)+I14*(Assumptions!$C$8*Assumptions!$C$16+Assumptions!$C$17/Assumptions!$C$9) | J20: =J10*(Assumptions!$C$10*Assumptions!$C$16+Assumptions!$C$17)+J14*(Assumptions!$C$8*Assumptions!$C$16+Assumptions!$C$17/Assumptions!$C$9) | ... N20: =N10*(Assumptions!$C$10*Assumptions!$C$16+Assumptions!$C$17)+N14*(Assumptions!$C$8*Assumptions!$C$16+Assumptions!$C$17/Assumptions!$C$9)
A21: LLM inference (audits x cost per audit) | B21: $ | C21: =C15*Assumptions!$B$5 | D21: =D15*Assumptions!$B$5 | E21: =E15*Assumptions!$B$5 | F21: =F15*Assumptions!$B$5 | G21: =G15*Assumptions!$B$5 | H21: =H15*Assumptions!$B$5 | I21: =I15*Assumptions!$B$5 | J21: =J15*Assumptions!$B$5 | ... N21: =N15*Assumptions!$B$5
A22: Data (audits x data cost per audit) | B22: $ | C22: =C15*Assumptions!$C$15 | D22: =D15*Assumptions!$C$15 | E22: =E15*Assumptions!$C$15 | F22: =F15*Assumptions!$C$15 | G22: =G15*Assumptions!$C$15 | H22: =H15*Assumptions!$C$15 | I22: =I15*Assumptions!$C$15 | J22: =J15*Assumptions!$C$15 | ... N22: =N15*Assumptions!$C$15
A23: Gross profit | B23: $ | C23: =C19-C20-C21-C22 | D23: =D19-D20-D21-D22 | E23: =E19-E20-E21-E22 | F23: =F19-F20-F21-F22 | G23: =G19-G20-G21-G22 | H23: =H19-H20-H21-H22 | I23: =I19-I20-I21-I22 | J23: =J19-J20-J21-J22 | ... N23: =N19-N20-N21-N22
A24: Gross margin | B24: % | C24: =IF(C19=0,0,C23/C19) | D24: =IF(D19=0,0,D23/D19) | E24: =IF(E19=0,0,E23/E19) | F24: =IF(F19=0,0,F23/F19) | G24: =IF(G19=0,0,G23/G19) | H24: =IF(H19=0,0,H23/H19) | I24: =IF(I19=0,0,I23/I19) | J24: =IF(J19=0,0,J23/J19) | ... N24: =IF(N19=0,0,N23/N19)
A26: Marketing (new users x CAC) | B26: $ | C26: =C7*Assumptions!$C$22 | D26: =D7*Assumptions!$C$22 | E26: =E7*Assumptions!$C$22 | F26: =F7*Assumptions!$C$22 | G26: =G7*Assumptions!$C$22 | H26: =H7*Assumptions!$C$22 | I26: =I7*Assumptions!$C$22 | J26: =J7*Assumptions!$C$22 | ... N26: =N7*Assumptions!$C$22
A27: Hosting | B27: $ | C27: =Assumptions!$C$23 | D27: =Assumptions!$C$23 | E27: =Assumptions!$C$23 | F27: =Assumptions!$C$23 | G27: =Assumptions!$C$23 | H27: =Assumptions!$C$23 | I27: =Assumptions!$C$23 | J27: =Assumptions!$C$23 | ... N27: =Assumptions!$C$23
A28: neatlogs | B28: $ | C28: =Assumptions!$C$24 | D28: =Assumptions!$C$24 | E28: =Assumptions!$C$24 | F28: =Assumptions!$C$24 | G28: =Assumptions!$C$24 | H28: =Assumptions!$C$24 | I28: =Assumptions!$C$24 | J28: =Assumptions!$C$24 | ... N28: =Assumptions!$C$24
A29: Team | B29: $ | C29: =Assumptions!$C$25 | D29: =Assumptions!$C$25 | E29: =Assumptions!$C$25 | F29: =Assumptions!$C$25 | G29: =Assumptions!$C$25 | H29: =Assumptions!$C$25 | I29: =Assumptions!$C$25 | J29: =Assumptions!$C$25 | ... N29: =Assumptions!$C$25
A30: Operating profit | B30: $ | C30: =C23-C26-C27-C28-C29 | D30: =D23-D26-D27-D28-D29 | E30: =E23-E26-E27-E28-E29 | F30: =F23-F26-F27-F28-F29 | G30: =G23-G26-G27-G28-G29 | H30: =H23-H26-H27-H28-H29 | I30: =I23-I26-I27-I28-I29 | J30: =J23-J26-J27-J28-J29 | ... N30: =N23-N26-N27-N28-N29
A32: Cash, start of month | B32: $ | C32: =Assumptions!$C$26 | D32: =C33 | E32: =D33 | F32: =E33 | G32: =F33 | H32: =G33 | I32: =H33 | J32: =I33 | K32: =J33 | ... N32: =M33
A33: Cash, end of month | B33: $ | C33: =C32+C30 | D33: =D32+D30 | E33: =E32+E30 | F33: =F32+F30 | G33: =G32+G30 | H33: =H32+H30 | I33: =I32+I30 | J33: =J32+J30 | ... N33: =N32+N30
A35: Flag: cash below zero (1 = yes) | B35: flag | C35: =IF(C33<0,1,0) | D35: =IF(D33<0,1,0) | E35: =IF(E33<0,1,0) | F35: =IF(F33<0,1,0) | G35: =IF(G33<0,1,0) | H35: =IF(H33<0,1,0) | I35: =IF(I33<0,1,0) | J35: =IF(J33<0,1,0) | ... N35: =IF(N33<0,1,0)
A36: Flag: operating profit at or above zero (1 = yes) | B36: flag | C36: =IF(C30>=0,1,0) | D36: =IF(D30>=0,1,0) | E36: =IF(E30>=0,1,0) | F36: =IF(F30>=0,1,0) | G36: =IF(G30>=0,1,0) | H36: =IF(H30>=0,1,0) | I36: =IF(I30>=0,1,0) | J36: =IF(J30>=0,1,0) | ... N36: =IF(N30>=0,1,0)

Sheet Unit_Economics
A1: Unit economics: per audit and per subscriber
A2: LLM cost per audit is Assumptions!B5 (ESTIMATE until M2 measures it).
A3: Line | B3: Base | C3: Growth | D3: Unit
A4: One audit, pay per audit
A5: Price per audit | B5: =Assumptions!$B$8 | C5: =Assumptions!$C$8 | D5: $ / audit
A6: Payment fees per audit | B6: =Assumptions!$B$8*Assumptions!$B$16+Assumptions!$B$17/Assumptions!$B$9 | C6: =Assumptions!$C$8*Assumptions!$C$16+Assumptions!$C$17/Assumptions!$C$9 | D6: $ / audit
A7: LLM cost per audit (ESTIMATE) | B7: =Assumptions!$B$5 | C7: =Assumptions!$B$5 | D7: $ / audit
A8: Data cost per audit | B8: =Assumptions!$B$15 | C8: =Assumptions!$C$15 | D8: $ / audit
A9: Contribution per audit | B9: =B5-B6-B7-B8 | C9: =C5-C6-C7-C8 | D9: $ / audit
A10: Gross margin per audit | B10: =IF(B5=0,0,B9/B5) | C10: =IF(C5=0,0,C9/C5) | D10: %
A11: LLM cost per audit at which contribution is zero | B11: =B5-B6-B8 | C11: =C5-C6-C8 | D11: $ / audit
A12: One hobbyist subscriber, per month
A13: Plan price | B13: =Assumptions!$B$10 | C13: =Assumptions!$C$10 | D13: $ / month
A14: Payment fees | B14: =Assumptions!$B$10*Assumptions!$B$16+Assumptions!$B$17 | C14: =Assumptions!$C$10*Assumptions!$C$16+Assumptions!$C$17 | D14: $ / month
A15: LLM cost (audits run x cost per audit) | B15: =Assumptions!$B$12*Assumptions!$B$5 | C15: =Assumptions!$C$12*Assumptions!$B$5 | D15: $ / month
A16: Data cost | B16: =Assumptions!$B$12*Assumptions!$B$15 | C16: =Assumptions!$C$12*Assumptions!$C$15 | D16: $ / month
A17: Contribution per subscriber | B17: =B13-B14-B15-B16 | C17: =C13-C14-C15-C16 | D17: $ / month
A18: Gross margin per subscriber | B18: =IF(B13=0,0,B17/B13) | C18: =IF(C13=0,0,C17/C13) | D18: %
A19: Contribution if all included audits are used | B19: =B13-B14-Assumptions!$B$11*(Assumptions!$B$5+Assumptions!$B$15) | C19: =C13-C14-Assumptions!$C$11*(Assumptions!$B$5+Assumptions!$C$15) | D19: $ / month
A20: Revenue per audit actually run on the plan | B20: =IF(Assumptions!$B$12=0,0,B13/Assumptions!$B$12) | C20: =IF(Assumptions!$C$12=0,0,C13/Assumptions!$C$12) | D20: $ / audit
A21: One paying user, blended, per month
A22: Contribution per pay-per-audit user | B22: =Assumptions!$B$13*B9 | C22: =Assumptions!$C$13*C9 | D22: $ / month
A23: Blended contribution per user | B23: =Assumptions!$B$14*B17+(1-Assumptions!$B$14)*B22 | C23: =Assumptions!$C$14*C17+(1-Assumptions!$C$14)*C22 | D23: $ / month
A24: Acquisition cost (CAC) | B24: =Assumptions!$B$22 | C24: =Assumptions!$C$22 | D24: $ / user
A25: CAC payback | B25: =IF(B23<=0,"n/a",B24/B23) | C25: =IF(C23<=0,"n/a",C24/C23) | D25: months
A26: Lifetime value (LTV) | B26: =IF(Assumptions!$B$21=0,"n/a",B23/Assumptions!$B$21) | C26: =IF(Assumptions!$C$21=0,"n/a",C23/Assumptions!$C$21) | D26: $
A27: LTV to CAC | B27: =IF(B24=0,"n/a",B26/B24) | C27: =IF(C24=0,"n/a",C26/C24) | D27: x
A29: LTV = blended contribution per user / monthly churn. Payback = CAC / blended contribution. Contribution counts payment fees, LLM and data; hosting, neatlogs and team are fixed costs on the model sheets.
